ecsdep/__init__.py
ecsdep/ecsdep.py
ecsdep/tasks.py
ecsdep/terraform.py
ecsdep/templates/aws-policy.json
ecsdep/templates/ecs-cluster/auto-scaling.tf
ecsdep/templates/ecs-cluster/declares.tf
ecsdep/templates/ecs-cluster/declares.tfignore
ecsdep/templates/ecs-cluster/ecs-cluster.tf
ecsdep/templates/ecs-cluster/launch-configuration.tf
ecsdep/templates/ecs-cluster/load-balancer.tf
ecsdep/templates/ecs-cluster/nat.tf
ecsdep/templates/ecs-cluster/public-s3.tf
ecsdep/templates/ecs-cluster/roles.tf
ecsdep/templates/ecs-cluster/route53.tf
ecsdep/templates/ecs-cluster/security-group.tf
ecsdep/templates/ecs-cluster/vpc.tf
ecsdep/templates/ecs-cluster/vpc_peering.tf
ecsdep/templates/ecs-cluster/policies/ec2-role.json
ecsdep/templates/ecs-cluster/policies/ecs-ec2-role-policy.json
ecsdep/templates/ecs-cluster/policies/ecs-role.json
ecsdep/templates/ecs-cluster/policies/ecs-secret-read.json
ecsdep/templates/ecs-cluster/policies/ecs-service-auto-scaling-role.json
ecsdep/templates/ecs-cluster/policies/ecs-task-role.json
ecsdep/templates/task-def/data.tf
ecsdep/templates/task-def/declares.tf
ecsdep/templates/task-def/declares.tfignore
ecsdep/templates/task-def/service.tf
ecsdep-0.2.14.dist-info/LICENSE
ecsdep-0.2.14.dist-info/METADATA
ecsdep-0.2.14.dist-info/WHEEL
ecsdep-0.2.14.dist-info/entry_points.txt
ecsdep-0.2.14.dist-info/top_level.txt
ecsdep-0.2.14.dist-info/RECORD
