Metadata-Version: 2.1
Name: ecsdep
Version: 0.2.14
Summary: AWS ECS Deployment Tool With Terraform
Home-page: https://gitlab.com/skitai/ecsdep
Author: Hans Roh
Author-email: hansroh@gmail.com
License: MIT
Download-URL: https://pypi.python.org/pypi/ecsdep
Platform: posix
Classifier: License :: OSI Approved :: MIT License
Classifier: Development Status :: 3 - Alpha
Classifier: Topic :: Utilities
Classifier: Environment :: Console
Classifier: Topic :: Software Development :: Libraries :: Python Modules
Classifier: Intended Audience :: Developers
Classifier: Programming Language :: Python
Classifier: Programming Language :: Python :: 3
License-File: LICENSE
Requires-Dist: click
Requires-Dist: PyYAML
